setup.cfg
setup.py
PandaSurvey/__init__.py
PandaSurvey/base.py
PandaSurvey/simple.py
PandaSurvey.egg-info/PKG-INFO
PandaSurvey.egg-info/SOURCES.txt
PandaSurvey.egg-info/dependency_links.txt
PandaSurvey.egg-info/requires.txt
PandaSurvey.egg-info/top_level.txt
tests/__init__.py
tests/test_init.py
tests/datasets/__init__.py
tests/datasets/test_read_data.py
tests/rake/__init__.py
tests/rake/test_rake.py