Metadata-Version: 1.1
Name: PandaSurvey
Version: 0.111
Summary: Survey weighting utility for the Pandas DataFrame
Home-page: http://www.incontextsolutions.com/
Author: InContext Solutions
Author-email: quant@incontextsolutions.com
License: UNKNOWN
Download-URL: https://github.com/InContextSolutions/PandaSurvey/tarball/v0.1
Keywords: raking,Pandas,survey
Platform: UNKNOWN
